autofront/__init__.py
autofront/autofront.py
autofront/config.py
autofront/debug.py
autofront/detect.py
autofront/input_utilities.py
autofront/multi.py
autofront/parse.py
autofront/utilities.py
autofront/static/css/main.css
autofront/static/css/normalize.css
autofront/templates/check.html
autofront/templates/functions.html
autofront/templates/web_input.html
autofront/tests/README.txt
autofront/tests/autoled.py
autofront/tests/autotest.py
autofront/tests/background_script.py
autofront/tests/bugged_script.py
autofront/tests/conditional_input_script.py
autofront/tests/detect_script.py
autofront/tests/detect_test.py
autofront/tests/duplicate_title.py
autofront/tests/empty_args.py
autofront/tests/get_display_test.py
autofront/tests/import_script.py
autofront/tests/input_import.py
autofront/tests/input_script.py
autofront/tests/kwarg_test.py
autofront/tests/logger.txt
autofront/tests/main_test.py
autofront/tests/main_test_script.py
autofront/tests/remote_led.py
autofront/tests/simple_args.py
autofront/tests/simple_functions.py
autofront/tests/simple_name.py
autofront/tests/simple_script.py
autofront/tests/simple_script_args.py
autofront/tests/simple_script_live.py
autofront/tests/simple_test.py
autofront/tests/statictest.py
autofront/tests/templatetest.py
autofront/tests/test_joelle.py
autofront/tests/timeout.py
autofront/tests/static/css/main.css
autofront/tests/templates/functions.html
autofront-0.1.1a5.dist-info/LICENSE.txt
autofront-0.1.1a5.dist-info/METADATA
autofront-0.1.1a5.dist-info/WHEEL
autofront-0.1.1a5.dist-info/top_level.txt
autofront-0.1.1a5.dist-info/RECORD
