Metadata-Version: 2.1
Name: autofront
Version: 0.1.1a5
Summary: Automatic front end for Python project
Home-page: https://github.com/JimmyLamothe/autofront
Author: Jean-Michel Laprise
Author-email: jmichel.dev@gmail.com
License: BSD
Project-URL: Documentation, https://github.com/JimmyLamothe/autofront/wiki
Keywords: automatic frontend front-end web browser interface flask school
Platform: UNKNOWN
Classifier: Development Status :: 3 - Alpha
Classifier: Intended Audience :: Developers
Classifier: Topic :: Software Development :: User Interfaces
Classifier: Topic :: Internet :: WWW/HTTP :: Dynamic Content
Classifier: Topic :: Home Automation
Classifier: Programming Language :: Python :: 3
Classifier: License :: OSI Approved :: BSD License
Classifier: Operating System :: OS Independent
Requires-Python: >=3.6
Requires-Dist: flask
